kiwiurn/__init__.py
kiwiurn/urn.py
kiwiurn-0.0.3.dist-info/METADATA
kiwiurn-0.0.3.dist-info/WHEEL
kiwiurn-0.0.3.dist-info/top_level.txt
kiwiurn-0.0.3.dist-info/RECORD
